{
  "league": "championsleague",
  "season": "",
  "lastUpdated": "2025-11-22T12:46:03.325643",
  "lineups": [
    {
      "homeTeam": "Galatasaray",
      "awayTeam": "Stgilloise",
      "dateTime": "2025-11-25T18:45:00Z",
      "matchday": 5,
      "phase": "gruppenphase",
      "homeLineup": [
        "Victor Osimhen",
        "Baris Alper Yilmaz",
        "Mauro Icardi",
        "Leroy Sane",
        "Lucas Torreira",
        "Mario Lemina",
        "Ismail Jakobs",
        "Abdulkerim Bardakcı",
        "Davinson Sanchez",
        "Wilfried Singo",
        "Ugurcan Cakir"
      ],
      "awayLineup": [
        "Kevin Rodriguez",
        "Anouar Ait El Hadj",
        "Ousseynou Niang",
        "Rob Schoofs",
        "Kamiel Van De Perre",
        "Adem Zorgane",
        "Anan Khalaili",
        "Fedde Leysen",
        "Christian Burgess",
        "Kevin Mac Allister",
        "Kjell Scherpen"
      ]
    },
    {
      "homeTeam": "Ajaxamsterdam",
      "awayTeam": "Benfica",
      "dateTime": "2025-11-25T18:45:00Z",
      "matchday": 5,
      "phase": "gruppenphase",
      "homeLineup": [
        "Wout Weghorst",
        "Mika Godts",
        "Oscar Gloukh",
        "Oliver Edvardsen",
        "Kenneth Taylor",
        "Youri Regeer",
        "Gerald Alders",
        "Youri Baas",
        "Josip Sutalo",
        "Lucas Rosa",
        "Remko Pasveer"
      ],
      "awayLineup": [
        "Vangelis Pavlidis",
        "Fredrik Aursnes",
        "Georgiy Sudakov",
        "Dodi Lukebakio",
        "Enzo Barrenechea",
        "Richard Rios",
        "Samuel Dahl",
        "Antonio Silva",
        "Tomas Araujo",
        "Amar Dedic",
        "Anatoliy Trubin"
      ]
    },
    {
      "homeTeam": "Mancity",
      "awayTeam": "Leverkusen",
      "dateTime": "2025-11-25T21:00:00Z",
      "matchday": 5,
      "phase": "gruppenphase",
      "homeLineup": [
        "Jeremy Doku",
        "Erling Haaland",
        "Rayan Cherki",
        "Phil Foden",
        "Nico Gonzalez",
        "Bernardo Silva",
        "Nico O&#039;Reilly",
        "Josko Gvardiol",
        "Ruben Dias",
        "Matheus Nunes",
        "Gianluigi Donnarumma"
      ],
      "awayLineup": [
        "Patrik Schick",
        "Ernest Poku",
        "Jonas Hofmann",
        "Alejandro Grimaldo",
        "Aleix Garcia",
        "Ibrahim Maza",
        "Arthur",
        "Edmond Tapsoba",
        "Loic Bade",
        "Robert Andrich",
        "Mark Flekken"
      ]
    },
    {
      "homeTeam": "Sscneapel",
      "awayTeam": "Karabakh",
      "dateTime": "2025-11-25T21:00:00Z",
      "matchday": 5,
      "phase": "gruppenphase",
      "homeLineup": [
        "Eljif Elmas",
        "Rasmus Hojlund",
        "Matteo Politano",
        "Scott McTominay",
        "Stanislav Lobotka",
        "Frank Anguissa",
        "Miguel Gutierrez",
        "Alessandro Buongiorno",
        "Amir Rrahmani",
        "Giovanni Di Lorenzo",
        "Vanja Milinkovic-Savic"
      ],
      "awayLineup": [
        "Camilo Duran",
        "Abdellah Zoubir",
        "Leandro Andrade",
        "Kady Borges",
        "Marko Jankovic",
        "Pedro Bicalho",
        "Elvin Cafarquliyev",
        "Kevin Medina",
        "Bahlul Mustafazada",
        "Matheus Silva",
        "Mateusz Kochalski"
      ]
    },
    {
      "homeTeam": "Chelsea",
      "awayTeam": "Fcbarcelona",
      "dateTime": "2025-11-25T21:00:00Z",
      "matchday": 5,
      "phase": "gruppenphase",
      "homeLineup": [
        "Liam Delap",
        "Jamie Gittens",
        "Joao Pedro",
        "Pedro Neto",
        "Enzo Fernandez",
        "Andrey Santos",
        "Marc Cucurella",
        "Tosin Adarabioyo",
        "Trevoh Chalobah",
        "Reece James",
        "Robert Sanchez"
      ],
      "awayLineup": [
        "Marcus Rashford",
        "Robert Lewandowski",
        "Lamine Yamal",
        "Dani Olmo",
        "Frenkie de Jong",
        "Fermin Lopez",
        "Alejandro Balde",
        "Pau Cubarsi",
        "Ronald Araujo",
        "Eric Garcia",
        "Wojciech Szczesny"
      ]
    },
    {
      "homeTeam": "Dortmund",
      "awayTeam": "Villarreal",
      "dateTime": "2025-11-25T21:00:00Z",
      "matchday": 5,
      "phase": "gruppenphase",
      "homeLineup": [
        "Serhou Guirassy",
        "Carney Chukwuemeka",
        "Maximilian Beier",
        "Daniel Svensson",
        "Jobe Bellingham",
        "Pascal Gross",
        "Julian Ryerson",
        "Nico Schlotterbeck",
        "Emre Can",
        "Waldemar Anton",
        "Gregor Kobel"
      ],
      "awayLineup": [
        "Tani Oluwaseyi",
        "Gerard Moreno",
        "Alberto Moleiro",
        "Thomas Partey",
        "Santi Comesana",
        "Tajon Buchanan",
        "Alfonso Pedraza",
        "Renato Veiga",
        "Rafa Marin",
        "Pau Navarro",
        "Luiz Junior"
      ]
    },
    {
      "homeTeam": "Slaviaprag",
      "awayTeam": "Athbilbao",
      "dateTime": "2025-11-25T21:00:00Z",
      "matchday": 5,
      "phase": "gruppenphase",
      "homeLineup": [
        "Tomas Chory",
        "Youssoupha Sanyang",
        "Lukas Provod",
        "Youssoupha Mbodji",
        "Michal Sadilek",
        "Christos Zafeiris",
        "David Moses",
        "Stepan Chaloupek",
        "David Zima",
        "Tomas Vlcek",
        "Jindrich Stanek"
      ],
      "awayLineup": [
        "Gorka Guruzeta",
        "Nico Williams",
        "Selton Sued Sanchez Camilo",
        "Alex Berenguer",
        "Mikel Jauregizar",
        "Inigo Ruiz de Galarreta",
        "Yuri Berchiche",
        "Aymeric Laporte",
        "Dani Vivian",
        "Andoni Gorosabel",
        "Unai Simon"
      ]
    },
    {
      "homeTeam": "Olmarseille",
      "awayTeam": "Newcastle",
      "dateTime": "2025-11-25T21:00:00Z",
      "matchday": 5,
      "phase": "gruppenphase",
      "homeLineup": [
        "Pierre-Emerick Aubameyang",
        "Igor Paixao",
        "Angel Gomes",
        "Mason Greenwood",
        "Arthur Vermeeren",
        "Geoffrey Kondogbia",
        "Emerson",
        "Leonardo Balerdi",
        "Benjamin Pavard",
        "Timothy Weah",
        "Jeffrey de Lange"
      ],
      "awayLineup": [
        "Harvey Barnes",
        "Nick Woltemade",
        "Jacob Murphy",
        "Joelinton",
        "Sandro Tonali",
        "Bruno Guimaraes",
        "Dan Burn",
        "Sven Botman",
        "Malick Thiaw",
        "Kieran Trippier",
        "Nick Pope"
      ]
    },
    {
      "homeTeam": "Bodoeglimt",
      "awayTeam": "Juventusturin",
      "dateTime": "2025-11-25T21:00:00Z",
      "matchday": 5,
      "phase": "gruppenphase",
      "homeLineup": [
        "Ole Didrik Blomberg",
        "Kasper Høgh",
        "Isak Dybvik Maatta",
        "Sondre Fet",
        "Patrick Berg",
        "Sondre Auklend",
        "Fredrik Bjorkan",
        "Odin Luras Bjortuft",
        "Brede Moe",
        "Fredrik Sjovold",
        "Nikita Haikin"
      ],
      "awayLineup": [
        "Dusan Vlahovic",
        "Kenan Yildiz",
        "Francisco Conceicao",
        "Andrea Cambiaso",
        "Khephren Thuram",
        "Manuel Locatelli",
        "Weston McKennie",
        "Teun Koopmeiners",
        "Daniele Rugani",
        "Pierre Kalulu",
        "Michele Di Gregorio"
      ]
    },
    {
      "homeTeam": "Kopenhagen",
      "awayTeam": "Kairat",
      "dateTime": "2025-11-26T18:45:00Z",
      "matchday": 5,
      "phase": "gruppenphase",
      "homeLineup": [
        "Viktor Claesson",
        "Andreas Cornelius",
        "Elias Achouri",
        "Mads Emil Madsen",
        "Lukas Lerager",
        "Mohamed Elyounoussi",
        "Marcos Lopez",
        "Munashe Garananga",
        "Pantelis Hatzidiakos",
        "Junnosuke Suzuki",
        "Dominik Kotarski"
      ],
      "awayLineup": [
        "Edmilson",
        "Dastan Satpaev",
        "Jorginho",
        "Valeriy Gromyko",
        "Ofri Arad",
        "Damir Kasabulat",
        "Luis Mata",
        "Egor Sorokin",
        "Aleksandr Shirobokov",
        "Aleksandr Mrynskiy",
        "Temirlan Anarbekov"
      ]
    },
    {
      "homeTeam": "Aeppaphosfc",
      "awayTeam": "Monaco",
      "dateTime": "2025-11-26T18:45:00Z",
      "matchday": 5,
      "phase": "gruppenphase",
      "homeLineup": [
        "Vlad Dragomir",
        "Domingos Quina",
        "Pepe",
        "Ivan Sunjic",
        "Mislav Orsic",
        "Ken Sema",
        "David Goldar",
        "David Luiz",
        "Derrick Luckassen",
        "Bruno",
        "Neofytos Michail"
      ],
      "awayLineup": [
        "Mika Biereth",
        "Folarin Balogun",
        "Kassoum Ouattara",
        "Aleksandr Golovin",
        "Maghnes Akliouche",
        "Jordan Teze",
        "Mamadou Coulibaly",
        "Caio Henrique",
        "Mohammed Salisu",
        "Thilo Kehrer",
        "Philipp Kohn"
      ]
    },
    {
      "homeTeam": "Atlmadrid",
      "awayTeam": "Intermailand",
      "dateTime": "2025-11-26T21:00:00Z",
      "matchday": 5,
      "phase": "gruppenphase",
      "homeLineup": [
        "Julian Alvarez",
        "Alexander Sørloth",
        "Alex Baena",
        "Koke",
        "Pablo Barrios",
        "Giuliano Simeone",
        "Matteo Ruggeri",
        "David Hancko",
        "Jose Maria Gimenez",
        "Marcos Llorente",
        "Jan Oblak"
      ],
      "awayLineup": [
        "Lautaro Martinez",
        "Ange-Yoan Bonny",
        "Federico Dimarco",
        "Petar Sucic",
        "Hakan Calhanoglu",
        "Nicolo Barella",
        "Denzel Dumfries",
        "Alessandro Bastoni",
        "Francesco Acerbi",
        "Manuel Akanji",
        "Yann Sommer"
      ]
    },
    {
      "homeTeam": "Olympiakos",
      "awayTeam": "Realmadrid",
      "dateTime": "2025-11-26T21:00:00Z",
      "matchday": 5,
      "phase": "gruppenphase",
      "homeLineup": [
        "Ayoub El Kaabi",
        "Daniel Podence",
        "Chiquinho",
        "Gelson Martins",
        "Diogo Nascimento",
        "Christos Mouzakitis",
        "Francisco Ortega",
        "Lorenzo Pirola",
        "Panagiotis Retsos",
        "Rodinei",
        "Konstantinos Tzolakis"
      ],
      "awayLineup": [
        "Kylian Mbappe",
        "Vinicius Junior",
        "Jude Bellingham",
        "Brahim Diaz",
        "Eduardo Camavinga",
        "Arda Guler",
        "Alvaro Fernandez Carreras",
        "Dean Huijsen",
        "Raul Asencio",
        "Federico Valverde",
        "Thibaut Courtois"
      ]
    },
    {
      "homeTeam": "Liverpool",
      "awayTeam": "Eindhoven",
      "dateTime": "2025-11-26T21:00:00Z",
      "matchday": 5,
      "phase": "gruppenphase",
      "homeLineup": [
        "Hugo Ekitike",
        "Florian Wirtz",
        "Dominik Szoboszlai",
        "Mohamed Salah",
        "Alexis Mac Allister",
        "Ryan Gravenberch",
        "Andrew Robertson",
        "Virgil van Dijk",
        "Ibrahima Konate",
        "Conor Bradley",
        "Giorgi Mamardashvili"
      ],
      "awayLineup": [
        "Guus Til",
        "Ivan Perisic",
        "Ismael Saibari",
        "Dennis Man",
        "Joey Veerman",
        "Mauro Junior",
        "Anass Salah-Eddine",
        "Yarek Gasiorowski",
        "Jerdy Schouten",
        "Sergino Dest",
        "Matej Kovar"
      ]
    },
    {
      "homeTeam": "Arsenal",
      "awayTeam": "Bayern",
      "dateTime": "2025-11-26T21:00:00Z",
      "matchday": 5,
      "phase": "gruppenphase",
      "homeLineup": [
        "Mikel Merino",
        "Leandro Trossard",
        "Eberechi Eze",
        "Bukayo Saka",
        "Declan Rice",
        "Martin Zubimendi",
        "Riccardo Calafiori",
        "Gabriel Magalhaes",
        "William Saliba",
        "Jurrien Timber",
        "David Raya"
      ],
      "awayLineup": [
        "Harry Kane",
        "Luis Diaz",
        "Serge Gnabry",
        "Michael Olise",
        "Leon Goretzka",
        "Joshua Kimmich",
        "Josip Stanisic",
        "Jonathan Tah",
        "Dayot Upamecano",
        "Konrad Laimer",
        "Manuel Neuer"
      ]
    },
    {
      "homeTeam": "Frankfurt",
      "awayTeam": "Bergamo",
      "dateTime": "2025-11-26T21:00:00Z",
      "matchday": 5,
      "phase": "gruppenphase",
      "homeLineup": [
        "Jonathan Burkardt",
        "Ansgar Knauff",
        "Fares Chaibi",
        "Ritsu Doan",
        "Ellyes Skhiri",
        "Mahmoud Dahoud",
        "Nathaniel Brown",
        "Arthur Theate",
        "Robin Koch",
        "Rasmus Kristensen",
        "Michael Zetterer"
      ],
      "awayLineup": [
        "Nikola Krstovic",
        "Ademola Lookman",
        "Lazar Samardzic",
        "Davide Zappacosta",
        "Mario Pasalic",
        "Ederson",
        "Raoul Bellanova",
        "Honest Ahanor",
        "Isak Hien",
        "Odilon Kossounou",
        "Marco Carnesecchi"
      ]
    },
    {
      "homeTeam": "Psg",
      "awayTeam": "Tottenham",
      "dateTime": "2025-11-26T21:00:00Z",
      "matchday": 5,
      "phase": "gruppenphase",
      "homeLineup": [
        "Khvicha Kvaratskhelia",
        "Senny Mayulu",
        "Kang-in Lee",
        "Fabian Ruiz",
        "Vitinha",
        "Joao Neves",
        "Lucas Hernandez",
        "Willian Pacho",
        "Ilya Zabarnyi",
        "Warren Zaire-Emery",
        "Lucas Chevalier"
      ],
      "awayLineup": [
        "Randal Kolo Muani",
        "Richarlison",
        "Xavi Simons",
        "Brennan Johnson",
        "Pape Matar Sarr",
        "Joao Palhinha",
        "Djed Spence",
        "Micky van de Ven",
        "Cristian Romero",
        "Pedro Porro",
        "Guglielmo Vicario"
      ]
    },
    {
      "homeTeam": "Sporting",
      "awayTeam": "Clubbruegge",
      "dateTime": "2025-11-26T21:00:00Z",
      "matchday": 5,
      "phase": "gruppenphase",
      "homeLineup": [
        "Luis Suarez",
        "Pedro Goncalves",
        "Francisco Trincao",
        "Geny Catamo",
        "Joao Simoes",
        "Morten Hjulmand",
        "Maxi Araujo",
        "Goncalo Inacio",
        "Ousmane Diomande",
        "Ivan Fresneda",
        "Rui Silva"
      ],
      "awayLineup": [
        "Romeo Vermant",
        "Christos Tzolis",
        "Hans Vanaken",
        "Carlos Forbs",
        "Raphael Onyedika",
        "Aleksandar Stankovic",
        "Joaquin Seys",
        "Brandon Mechele",
        "Joel Ordonez",
        "Kyriani Sabbe",
        "Nordin Jackers"
      ]
    }
  ]
}