{
  "league": "2bundesliga",
  "season": "",
  "lastUpdated": "2025-11-21T17:48:32.688668",
  "lineups": [
    {
      "homeTeam": "VfL Bochum",
      "awayTeam": "Dynamo Dresden",
      "dateTime": "2025-11-21T18:30:00",
      "matchday": 13,
      "phase": "",
      "homeLineup": [
        "Francis Onyeka",
        "Gerrit Holtmann",
        "Kjell Watjen",
        "Farid Alfa-Ruprecht",
        "Mats Pannewig",
        "Cajetan Lenz",
        "Maximilian Wittek",
        "Philipp Strompf",
        "Noah Loosli",
        "Felix Passlack",
        "Timo Horn"
      ],
      "awayLineup": [
        "Vincent Vermeij",
        "Luca Herrmann",
        "Niklas Hauptmann",
        "Jakob Lemmer",
        "Friedrich Muller",
        "Kofi Amoako",
        "Alexander Rossipal",
        "Julian Pauli",
        "Lukas Boeder",
        "Konrad Faber",
        "Lennart Grill"
      ]
    },
    {
      "homeTeam": "Hertha BSC",
      "awayTeam": "Eintracht Braunschweig",
      "dateTime": "2025-11-21T18:30:00",
      "matchday": 13,
      "phase": "",
      "homeLineup": [
        "Luca Schuler",
        "Fabian Reese",
        "Michael Cuisance",
        "Marten Winkler",
        "Paul Seguin",
        "Diego Demme",
        "Michal Karbownik",
        "Marton Dardai",
        "Toni Leistner",
        "Linus Gechter",
        "Tjark Ernst"
      ],
      "awayLineup": [
        "Sidi Guessor Sane",
        "Leon Bell Bell",
        "Christian Conteh",
        "Fabio Di Michele Sanchez",
        "Sven Kohler",
        "Florian Flick",
        "Mehmet Aydin",
        "Lukas Frenkert",
        "Salomon Patrick Amougou Nkoa",
        "Kevin Ehlers",
        "Ron-Thorben Hoffmann"
      ]
    },
    {
      "homeTeam": "SC Paderborn 07",
      "awayTeam": "Hannover 96",
      "dateTime": "2025-11-22T13:00:00",
      "matchday": 13,
      "phase": "",
      "homeLineup": [
        "Steffen Tigges",
        "Stefano Marino",
        "Sebastian Klaas",
        "Raphael Obermair",
        "Mika Baur",
        "Filip Bilbija",
        "Laurin Curda",
        "Tjark Scheller",
        "Felix Gotze",
        "Mattes Hansen",
        "Dennis Seimen"
      ],
      "awayLineup": [
        "Husseyn Chakroun",
        "Benjamin Kallman",
        "Waniss Taibi",
        "Noel Aseko",
        "Kolja Oudenne",
        "Enzo Leopold",
        "Hayate Matsuda",
        "Maik Nawrocki",
        "Boris Tomiak",
        "Ime Okon",
        "Nahuel Noll"
      ]
    },
    {
      "homeTeam": "Fortuna Düsseldorf",
      "awayTeam": "1. FC Magdeburg",
      "dateTime": "2025-11-22T13:00:00",
      "matchday": 13,
      "phase": "",
      "homeLineup": [
        "Cedric Itten",
        "Florent Muslija",
        "Anouar El Azzouzi",
        "Christian Rasmussen",
        "Kenneth Schmidt",
        "Tim Breithaupt",
        "Emmanuel Iyoha",
        "Jesper Daland",
        "Tim Oberdorf",
        "Matthias Zimmermann",
        "Florian Kastenmeier"
      ],
      "awayLineup": [
        "Laurin Ulrich",
        "Alexander Ahl-Holmstrom",
        "Rayan Ghrieb",
        "Alexander Nollenberger",
        "Falko Michel",
        "Silas Gnaka",
        "Lubambo Musonda",
        "Max Geschwill",
        "Luka Hyrylainen",
        "Marcus Mathisen",
        "Dominik Reimann"
      ]
    },
    {
      "homeTeam": "Preußen Münster",
      "awayTeam": "FC Schalke 04",
      "dateTime": "2025-11-22T13:00:00",
      "matchday": 13,
      "phase": "",
      "homeLineup": [
        "Lars Lokotsch",
        "Oliver Batista Meier",
        "Zidan Sertdemir",
        "Jorrit Hendrix",
        "Rico Preissinger",
        "Yassine Bouchama",
        "Mikkel Kirkeskov",
        "Paul Jaeckel",
        "Jannis Heuer",
        "Jano ter Horst",
        "Johannes Schenk"
      ],
      "awayLineup": [
        "Moussa Sylla",
        "Mika Tom Wallentowitz",
        "Kenan Karaman",
        "Soufiane El-Faouzi",
        "Ron Schallenberg",
        "Finn Porath",
        "Vitalie Becker",
        "Hasan Kurucay",
        "Nikola Katic",
        "Mertcan Ayhan",
        "Loris Karius"
      ]
    },
    {
      "homeTeam": "SV Darmstadt 98",
      "awayTeam": "SpVgg Greuther Fürth",
      "dateTime": "2025-11-22T20:30:00",
      "matchday": 13,
      "phase": "",
      "homeLineup": [
        "Isac Lidberg",
        "Luca Marseiler",
        "Fraser Hornby",
        "Killian Corredor",
        "Hiroki Akiyama",
        "Kai Klefisch",
        "Fabian Holland",
        "Matej Maglica",
        "Patric Pfeiffer",
        "Sergio Lopez",
        "Marcel Schuhen"
      ],
      "awayLineup": [
        "Branimir Hrgota",
        "Noel Futkeu",
        "Felix Klaus",
        "David Abrangao",
        "Julian Green",
        "Mathias Olesen",
        "Lukas Reich",
        "Luca Itter",
        "Reno Munz",
        "Maximilian Dietz",
        "Silas Prufrock"
      ]
    },
    {
      "homeTeam": "1. FC Kaiserslautern",
      "awayTeam": "Holstein Kiel",
      "dateTime": "2025-11-23T13:30:00",
      "matchday": 13,
      "phase": "",
      "homeLineup": [
        "Daniel Hanslik",
        "Ivan Prtajin",
        "Mika Haas",
        "Semih Sahin",
        "Naatan Skytta",
        "Paul Joly",
        "Fabian Kunze",
        "Leon Robinson",
        "Maxwell Gyamfi",
        "Luca Sirch",
        "Julian Krahl"
      ],
      "awayLineup": [
        "Adrian Kapralik",
        "Jonas Therkelsen",
        "Alexander Bernhardsson",
        "John Tolkin",
        "Stefan Schwab",
        "Kasper Davidsen",
        "Lasse Rosenboom",
        "Marco Komenda",
        "Carl Johansson",
        "David Zec",
        "Jonas Krumrey"
      ]
    },
    {
      "homeTeam": "Karlsruher SC",
      "awayTeam": "SV 07 Elversberg",
      "dateTime": "2025-11-23T13:30:00",
      "matchday": 13,
      "phase": "",
      "homeLineup": [
        "Leon Opitz",
        "Fabian Schleusener",
        "David Herold",
        "Marvin Wanitzek",
        "Dzenis Burnic",
        "Philipp Forster",
        "Rafael Pinto Pedrosa",
        "Nicolai Rapp",
        "Marcel Franke",
        "Christoph Kobald",
        "Hans Christian Bernat"
      ],
      "awayLineup": [
        "Younes Ebnoutalib",
        "Tom Zimmerschied",
        "Bambase Conte",
        "Lukas Petkov",
        "Lukasz Poreba",
        "Amara Conde",
        "Felix Keidel",
        "Maximilian Rohr",
        "Lukas Pinckert",
        "Jan Gyamerah",
        "Nicolas Kristof"
      ]
    },
    {
      "homeTeam": "1. FC Nürnberg",
      "awayTeam": "Arminia Bielefeld",
      "dateTime": "2025-11-23T13:30:00",
      "matchday": 13,
      "phase": "",
      "homeLineup": [
        "Artem Stepanov",
        "Rafael Lubach",
        "Adam Markhiev",
        "Finn Becker",
        "Julian Justvan",
        "Berkay Yilmaz",
        "Robin Knoche",
        "Fabio Gruber",
        "Tim Janisch",
        "Jan Reichert"
      ],
      "awayLineup": [
        "Noah Sarenren Bazee",
        "Joel Grodowski",
        "Monju Momuluh",
        "Tim Handwerker",
        "Marius Worl",
        "Mael Corboz",
        "Benjamin Boakye",
        "Joel Felix",
        "Maximilian Grosser",
        "Leon Schneider",
        "Jonas Kersken"
      ]
    }
  ]
}